Metadata-Version: 2.1
Name: switchbotpy
Version: 0.1.3
Summary: An API for Switchbots that allows to control actions, settings and timers (also password protected)
Home-page: https://github.com/RoButton/switchbotpy
Author: Nicolas Küchler
Author-email: nico.kuechler@protonmail.com
License: MIT
Download-URL: https://github.com/RoButton/switchbotpy/archive/v_10.tar.gz
Keywords: Switchbot,Ble,Button,Actions,Settings,Timers
Platform: UNKNOWN
Classifier: Development Status :: 3 - Alpha
Classifier: Intended Audience :: Developers
Classifier: Topic :: Software Development :: Build Tools
Classifier: License :: OSI Approved :: MIT License
Classifier: Programming Language :: Python :: 3.6
Classifier: Programming Language :: Python :: 3.7
Classifier: Programming Language :: Python :: 3.8
